odoo/addons/sale_commission_margin/README.rst
odoo/addons/sale_commission_margin/__init__.py
odoo/addons/sale_commission_margin/__manifest__.py
odoo/addons/sale_commission_margin/i18n/it.po
odoo/addons/sale_commission_margin/i18n/pt_BR.po
odoo/addons/sale_commission_margin/i18n/sale_commission_margin.pot
odoo/addons/sale_commission_margin/models/__init__.py
odoo/addons/sale_commission_margin/models/commission_mixin.py
odoo/addons/sale_commission_margin/models/sale_order_line.py
odoo/addons/sale_commission_margin/readme/CONTRIBUTORS.md
odoo/addons/sale_commission_margin/readme/DESCRIPTION.md
odoo/addons/sale_commission_margin/readme/USAGE.md
odoo/addons/sale_commission_margin/static/description/icon.png
odoo/addons/sale_commission_margin/static/description/index.html
odoo/addons/sale_commission_margin/tests/__init__.py
odoo/addons/sale_commission_margin/tests/test_sale_order.py
odoo/addons/sale_commission_margin/views/sale_order_view.xml
odoo_addon_sale_commission_margin-16.0.1.0.0.5.dist-info/METADATA
odoo_addon_sale_commission_margin-16.0.1.0.0.5.dist-info/WHEEL
odoo_addon_sale_commission_margin-16.0.1.0.0.5.dist-info/top_level.txt
odoo_addon_sale_commission_margin-16.0.1.0.0.5.dist-info/RECORD
